[
    {
        "codigo": 1,
        "nome": "Mouse",
        "quantidade": 0,
        "preco": 20.0,
        "estoque_minimo": 10,
        "estoque_maximo": 100,
        "setor": "Almoxarifado"
    },
    {
        "codigo": 14,
        "nome": "Mousepad",
        "quantidade": 0,
        "preco": 15.0,
        "estoque_minimo": 2,
        "estoque_maximo": 10,
        "setor": "Almoxarifado"
    },
    {
        "codigo": 8,
        "nome": "PenDrive",
        "quantidade": 20,
        "preco": 50.0,
        "estoque_minimo": 10,
        "estoque_maximo": 30,
        "setor": "Almoxarifado"
    },
    {
        "codigo": 13,
        "nome": "Processador i3 14th",
        "quantidade": 3,
        "preco": 1000.0,
        "estoque_minimo": 1,
        "estoque_maximo": 5,
        "setor": "Almoxarifado"
    },
    {
        "codigo": 12,
        "nome": "SSD 480GB",
        "quantidade": 4,
        "preco": 200.0,
        "estoque_minimo": 5,
        "estoque_maximo": 10,
        "setor": "Almoxarifado"
    },
    {
        "codigo": 5,
        "nome": "Cabo HDMI",
        "quantidade": 8,
        "preco": 32.0,
        "estoque_minimo": 7,
        "estoque_maximo": 10,
        "setor": "TI"
    },
    {
        "codigo": 4,
        "nome": "Monitor",
        "quantidade": 2,
        "preco": 800.0,
        "estoque_minimo": 1,
        "estoque_maximo": 3,
        "setor": "TI"
    },
    {
        "codigo": 14,
        "nome": "Mousepad",
        "quantidade": 4,
        "preco": 15.0,
        "estoque_minimo": 3,
        "estoque_maximo": 10,
        "setor": "TI"
    },
    {
        "codigo": 13,
        "nome": "Processador i3 14th",
        "quantidade": 2,
        "preco": 1000.0,
        "estoque_minimo": 1,
        "estoque_maximo": 3,
        "setor": "TI"
    },
    {
        "codigo": 12,
        "nome": "SSD 480GB",
        "quantidade": 6,
        "preco": 200.0,
        "estoque_minimo": 5,
        "estoque_maximo": 15,
        "setor": "TI"
    }
]